{
  "missionId": "mission_20260205_194124_51mjpe",
  "status": "COMPLETED",
  "criteria": [
    {
      "id": "ISC-1770320490127-gusnr3",
      "text": "Public access blocked at bucket level completely",
      "satisfaction": "PENDING",
      "evidenceRefs": [],
      "createdAt": "2026-02-05T19:41:30.127Z",
      "confidence": 0.9714285714285713,
      "source": "agent_response"
    },
    {
      "id": "ISC-1770320490127-wizene",
      "text": "Server-side encryption enabled using AES256",
      "satisfaction": "PENDING",
      "evidenceRefs": [],
      "createdAt": "2026-02-05T19:41:30.127Z",
      "confidence": 0.9714285714285713,
      "source": "agent_response"
    },
    {
      "id": "ISC-1770320490127-c7nupk",
      "text": "Versioning enabled for data protection always",
      "satisfaction": "PENDING",
      "evidenceRefs": [],
      "createdAt": "2026-02-05T19:41:30.127Z",
      "confidence": 0.9714285714285713,
      "source": "agent_response"
    },
    {
      "id": "ISC-1770320490127-cxmexf",
      "text": "Server access logging enabled for audit trail",
      "satisfaction": "PENDING",
      "evidenceRefs": [],
      "createdAt": "2026-02-05T19:41:30.127Z",
      "confidence": 0.9714285714285713,
      "source": "agent_response"
    },
    {
      "id": "ISC-1770320490127-siidd7",
      "text": "Block public access setting enforced universally",
      "satisfaction": "PENDING",
      "evidenceRefs": [],
      "createdAt": "2026-02-05T19:41:30.127Z",
      "confidence": 0.9714285714285713,
      "source": "agent_response"
    },
    {
      "id": "ISC-1770320490127-knjas4",
      "text": "Default encryption configured for all objects",
      "satisfaction": "PENDING",
      "evidenceRefs": [],
      "createdAt": "2026-02-05T19:41:30.127Z",
      "confidence": 0.9714285714285713,
      "source": "agent_response"
    },
    {
      "id": "ISC-1770320490127-841hdp",
      "text": "Bucket policy restricts unauthenticated access completely",
      "satisfaction": "PENDING",
      "evidenceRefs": [],
      "createdAt": "2026-02-05T19:41:30.127Z",
      "confidence": 0.9714285714285713,
      "source": "agent_response"
    }
  ],
  "satisfaction": {
    "satisfied": 0,
    "failed": 0,
    "pending": 7,
    "total": 7,
    "rate": 0
  },
  "createdAt": "2026-02-05T19:41:24.514Z",
  "updatedAt": "2026-02-05T19:41:30.127Z"
}